translator/__init__.py
translator/__main__.py
translator/clip.py
translator/translate.py
ztranslator-1.0.0.dist-info/entry_points.txt
ztranslator-1.0.0.dist-info/LICENSE
ztranslator-1.0.0.dist-info/WHEEL
ztranslator-1.0.0.dist-info/METADATA
ztranslator-1.0.0.dist-info/RECORD
