Metadata-Version: 2.1
Name: ztranslator
Version: 1.0.0
Summary: Powerful command line translator.
License: MIT
Author: André P. Santos
Author-email: andreztz@gmail.com
Requires-Python: >=3.6.1,<4.0.0
Classifier: Development Status :: 1 - Planning
Classifier: Intended Audience :: Developers
Classifier: Intended Audience :: End Users/Desktop
Classifier: License :: OSI Approved :: MIT License
Classifier: Programming Language :: Python :: 3
Classifier: Programming Language :: Python :: 3 :: Only
Classifier: Programming Language :: Python :: 3.10
Classifier: Programming Language :: Python :: 3.7
Classifier: Programming Language :: Python :: 3.8
Classifier: Programming Language :: Python :: 3.9
Classifier: Topic :: Utilities
Requires-Dist: googletrans (==3.1.0a0)
Requires-Dist: notify-send (>=0.0.19,<0.0.20)
Requires-Dist: requests (>=2.23.0,<3.0.0)
